consumable/__init__.py
consumable-1.1.3.dist-info/LICENSE
consumable-1.1.3.dist-info/METADATA
consumable-1.1.3.dist-info/WHEEL
consumable-1.1.3.dist-info/RECORD
